tools/__init__.py
tools/main.py
tools/ratelimiter.py
tools/file_types/__init__.py
tools/file_types/file_type_db.py
tools/file_types/main.py
async_tools_ext-0.0.1.dist-info/LICENSE
async_tools_ext-0.0.1.dist-info/METADATA
async_tools_ext-0.0.1.dist-info/WHEEL
async_tools_ext-0.0.1.dist-info/top_level.txt
async_tools_ext-0.0.1.dist-info/RECORD
